HISTORY.md
MANIFEST.in
README.md
setup.py
workflow.png
src/__init__.py
src/__version__.py
src/cli.py
src/exceptions.py
src/help.py
src/models.py
src/status_codes.py
src/utils.py
src/templates/__init__.py
src/templates/__version__.py
src/templates/setup.py
startpkg.egg-info/PKG-INFO
startpkg.egg-info/SOURCES.txt
startpkg.egg-info/dependency_links.txt
startpkg.egg-info/entry_points.txt
startpkg.egg-info/not-zip-safe
startpkg.egg-info/requires.txt
startpkg.egg-info/top_level.txt